CHANGELOG.txt
LICENCE.txt
MANIFEST.in
README.txt
sample.py
sample.txt
setup.cfg
setup.py
pyls_smart/__init__.py
pyls_smart.egg-info/PKG-INFO
pyls_smart.egg-info/SOURCES.txt
pyls_smart.egg-info/dependency_links.txt
pyls_smart.egg-info/entry_points.txt
pyls_smart.egg-info/top_level.txt
sample/file.txt
sample/one/one.txt
tests/__init__.py
tests/list_directory.py