Metadata-Version: 1.1
Name: pyls-smart
Version: 0.0.1
Summary: A command to list directory
Home-page: https://github.com/vickyrv2206/python_project
Author: Vignesh Ramesh
Author-email: vickyvignesh2206@gmail.com
License: MIT
Keywords: list-directory
Platform: UNKNOWN
Classifier: Development Status :: 5 - Production/Stable
Classifier: Intended Audience :: End Users/Desktop
Classifier: Operating System :: Unix
Classifier: License :: OSI Approved :: MIT License
Classifier: Programming Language :: Python :: 3
